uvdiviner/__init__.py
uvdiviner/colorize.py
uvdiviner/divine.py
uvdiviner/errors.py
uvdiviner/evolution.py
uvdiviner/main.py
uvdiviner/progressbar.py
uvdiviner/settings.py
uvdiviner/trigrams.py
uvdiviner-2.2.0.dist-info/LICENSE
uvdiviner-2.2.0.dist-info/METADATA
uvdiviner-2.2.0.dist-info/WHEEL
uvdiviner-2.2.0.dist-info/top_level.txt
uvdiviner-2.2.0.dist-info/RECORD
