Metadata-Version: 2.1
Name: uvdiviner
Version: 2.2.0
Summary: 基于周易蓍草占卜原理实现的中国古占卜.
Home-page: https://gitee.com/unvisitor/diviner
Author: Night Resurgent <fu050409@163.com>
Author-email: fu050409@163.com
License: Apache-2.0
Project-URL: Bug Tracker, https://gitee.com/unvisitor/diviner/issues
Classifier: Programming Language :: Python :: 3
Classifier: License :: OSI Approved :: Apache Software License
Classifier: Operating System :: OS Independent
Requires-Python: >=3
License-File: LICENSE
Requires-Dist: colorama
